cocotbext/eth/__init__.py
cocotbext/eth/constants.py
cocotbext/eth/eth_mac.py
cocotbext/eth/gmii.py
cocotbext/eth/mii.py
cocotbext/eth/ptp.py
cocotbext/eth/reset.py
cocotbext/eth/rgmii.py
cocotbext/eth/version.py
cocotbext/eth/xgmii.py
cocotbext_eth-0.1.22.dist-info/LICENSE
cocotbext_eth-0.1.22.dist-info/METADATA
cocotbext_eth-0.1.22.dist-info/WHEEL
cocotbext_eth-0.1.22.dist-info/top_level.txt
cocotbext_eth-0.1.22.dist-info/RECORD
