Metadata-Version: 2.1
Name: cocotbext-eth
Version: 0.1.22
Summary: Ethernet interface modules for cocotb
Home-page: https://github.com/alexforencich/cocotbext-eth
Download-URL: https://github.com/alexforencich/cocotbext-eth/tarball/master
Author: Alex Forencich
Author-email: alex@alexforencich.com
License: MIT
Project-URL: Bug Tracker, https://github.com/alexforencich/cocotbext-eth/issues
Project-URL: Source Code, https://github.com/alexforencich/cocotbext-eth
Keywords: ethernet,cocotb
Platform: any
Classifier: Development Status :: 3 - Alpha
Classifier: Framework :: cocotb
Classifier: License :: OSI Approved :: MIT License
Classifier: Operating System :: OS Independent
Classifier: Programming Language :: Python :: 3
Classifier: Topic :: Scientific/Engineering :: Electronic Design Automation (EDA)
Requires-Python: >=3.6
License-File: LICENSE
Requires-Dist: cocotb>=1.6.0
Requires-Dist: cocotbext-axi>=0.1.16
Provides-Extra: test
Requires-Dist: pytest; extra == "test"
Requires-Dist: cocotb-test; extra == "test"
